testing_pycon_italy_2025/__init__.py
testing_pycon_italy_2025-0.1.0.dist-info/METADATA
testing_pycon_italy_2025-0.1.0.dist-info/WHEEL
testing_pycon_italy_2025-0.1.0.dist-info/entry_points.txt
testing_pycon_italy_2025-0.1.0.dist-info/RECORD
