Metadata-Version: 2.4
Name: testing_pycon_italy_2025
Version: 0.1.0
Summary: Add your description here
Author-email: Vinicius Gubiani Ferreira <vini.g.fer@gmail.com>
Requires-Python: >=3.8
Requires-Dist: requests>=2.32.3
